accmix/annotate.py
accmix/cli.py
accmix/evaluate.py
accmix/model_core.py
accmix/scanner.py
accmix/utils.py
accmix-0.2.0.dist-info/licenses/LICENSE
accmix-0.2.0.dist-info/METADATA
accmix-0.2.0.dist-info/WHEEL
accmix-0.2.0.dist-info/entry_points.txt
accmix-0.2.0.dist-info/top_level.txt
accmix-0.2.0.dist-info/RECORD
