Metadata-Version: 2.4
Name: accmix
Version: 0.2.0
Summary: RAD-seq EM mixture with logistic prior: scan, annotate, model, diff
Author: yangli04
License: Proprietary
Requires-Python: >=3.10
License-File: LICENSE
Requires-Dist: polars>=0.20
Requires-Dist: numpy>=1.24
Requires-Dist: scipy>=1.10
Requires-Dist: pyranges1>=1.1.6
Requires-Dist: metagene>=0.0.15
Requires-Dist: scikit-learn>=1.2
Requires-Dist: matplotlib>=3.7
Requires-Dist: seaborn>=0.12
Requires-Dist: pandas>=2.0
Requires-Dist: pyarrow>=12
Requires-Dist: numba>=0.57
Requires-Dist: tqdm>=4.65
Requires-Dist: typer>=0.11
Dynamic: license-file
